pydiscover
